Metadata-Version: 2.1
Name: TSIClient-raalabs
Version: 2.1.3
Summary: The TSIClient is a Python SDK for Microsoft Azure time series insights.
Home-page: https://github.com/RaaLabs/TSIClient
Author: Raa Labs
Author-email: post@raalabs.com
License: MIT
Project-URL: Bug Tracker, https://github.com/RaaLabs/TSIClient/issues
Project-URL: Documentation, https://raalabs-tsiclient.readthedocs.io/en/latest/
Project-URL: Source Code, https://github.com/RaaLabs/TSIClient
Keywords: Time Series Insights,TSI,TSI SDK,Raa Labs,IoT
Platform: UNKNOWN
Classifier: Development Status :: 3 - Alpha
Classifier: Intended Audience :: Developers
Classifier: Topic :: Software Development :: Build Tools
Classifier: License :: OSI Approved :: MIT License
Classifier: Programming Language :: Python :: 3.9
